pomsimulator/__init__.py
pomsimulator/modules/DataBase.py
pomsimulator/modules/__init__.py
pomsimulator/modules/graph_module.py
pomsimulator/modules/helper_module.py
pomsimulator/modules/msce_module.py
pomsimulator/modules/plotting_module.py
pomsimulator/modules/stats_module.py
pomsimulator/modules/text_module.py
pomsimulator-2.0.1.dist-info/LICENSE.txt
pomsimulator-2.0.1.dist-info/METADATA
pomsimulator-2.0.1.dist-info/WHEEL
pomsimulator-2.0.1.dist-info/top_level.txt
pomsimulator-2.0.1.dist-info/RECORD
