Metadata-Version: 2.1
Name: pomsimulator
Version: 2.0.1
Summary: Simulate the aqueous speciation of polyoxometalates (POMs) from quantum mechanical results
Author: Enric Petrus, Jordi Buils, Diego Garay-Ruiz
Author-email: enricpz@icloud.com, jbuils@iciq.es, dgaray@iciq.es
License-File: LICENSE.txt
Requires-Dist: numpy >=1.17.3
Requires-Dist: matplotlib >=3.1.2
Requires-Dist: networkx >=2.4
Requires-Dist: scipy >=1.6.1
Requires-Dist: pandas >=1.5
Requires-Dist: scikit-learn >=1.3.2
Requires-Dist: seaborn
Requires-Dist: setuptools
